reader/__init__.py
reader/__main__.py
reader/config.cfg
reader/feed.py
reader/viewer.py
mltrackingclient-1.0.1.dist-info/LICENSE
mltrackingclient-1.0.1.dist-info/METADATA
mltrackingclient-1.0.1.dist-info/WHEEL
mltrackingclient-1.0.1.dist-info/entry_points.txt
mltrackingclient-1.0.1.dist-info/top_level.txt
mltrackingclient-1.0.1.dist-info/RECORD
