Metadata-Version: 2.1
Name: mltrackingclient
Version: 1.0.1
Summary: REST ML-AI API
Home-page: https://github.com/EimantasN/Equusight_BackEnd
Author: Eimantas Noreika
Author-email: noreika.eimantas@gmail.com
License: MIT
Platform: UNKNOWN
Classifier: License :: OSI Approved :: MIT License
Classifier: Programming Language :: Python :: 3
Classifier: Programming Language :: Python :: 3.6
Requires-Python: >=3.6
Requires-Dist: feedparser
Requires-Dist: html2text
Requires-Dist: importlib-resources
Requires-Dist: typing
